cloudflare_vectorize/__init__.py
cloudflare_vectorize/client.py
cloudflare_vectorize/exceptions.py
cloudflare_vectorize/utils.py
cloudflare_vectorize-0.1.2.dist-info/licenses/LICENSE
cloudflare_vectorize-0.1.2.dist-info/METADATA
cloudflare_vectorize-0.1.2.dist-info/WHEEL
cloudflare_vectorize-0.1.2.dist-info/top_level.txt
cloudflare_vectorize-0.1.2.dist-info/RECORD
