Metadata-Version: 2.4
Name: cloudflare-vectorize
Version: 0.1.2
Summary: Python client for Cloudflare Vectorize API
Author: ourines
Author-email: ourines@icloud.com
License: MIT
Classifier: Development Status :: 3 - Alpha
Classifier: Intended Audience :: Developers
Classifier: License :: OSI Approved :: MIT License
Classifier: Programming Language :: Python :: 3
Classifier: Programming Language :: Python :: 3.7
Classifier: Programming Language :: Python :: 3.8
Classifier: Programming Language :: Python :: 3.9
Classifier: Programming Language :: Python :: 3.10
Classifier: Programming Language :: Python :: 3.11
Requires-Python: >=3.7
License-File: LICENSE
Requires-Dist: requests<3.0.0,>=2.25.0
Requires-Dist: urllib3<2.0.0,>=1.26.0
Requires-Dist: typing-extensions>=4.0.0; python_version < "3.8"
Provides-Extra: dev
Requires-Dist: pytest>=6.0; extra == "dev"
Requires-Dist: pytest-cov>=2.0; extra == "dev"
Requires-Dist: black>=22.0; extra == "dev"
Requires-Dist: isort>=5.0; extra == "dev"
Requires-Dist: mypy>=0.900; extra == "dev"
Requires-Dist: types-requests>=2.25.0; extra == "dev"
Dynamic: license-file
